streamlit_modal/__init__.py
streamlit_modal-0.1.2.dist-info/LICENSE
streamlit_modal-0.1.2.dist-info/METADATA
streamlit_modal-0.1.2.dist-info/WHEEL
streamlit_modal-0.1.2.dist-info/top_level.txt
streamlit_modal-0.1.2.dist-info/RECORD
