Metadata-Version: 2.1
Name: streamlit-modal
Version: 0.1.2
Summary: Modal for streamlit
Home-page: https://github.com/teamtv/streamlit_modal
Author: Koen Vossen
Author-email: info@koenvossen.nl
License: BSD
Classifier: Intended Audience :: Developers
Classifier: Intended Audience :: Science/Research
Classifier: Programming Language :: Python :: 3
Classifier: Programming Language :: Python :: 3.6
Classifier: Programming Language :: Python :: 3.7
Classifier: Programming Language :: Python :: 3.8
Classifier: Programming Language :: Python :: 3.9
Classifier: Programming Language :: Python :: 3.10
Classifier: License :: OSI Approved
Classifier: Topic :: Scientific/Engineering
License-File: LICENSE
